README.md
setup.py
tests/__init__.py
tests/test_make_type.py
tests/test_numeric_constraints.py
tests/test_string_constraints.py
typefactory/__init__.py
typefactory.egg-info/PKG-INFO
typefactory.egg-info/SOURCES.txt
typefactory.egg-info/dependency_links.txt
typefactory.egg-info/top_level.txt
typefactory/constraints/__init__.py
typefactory/constraints/numeric.py
typefactory/constraints/string.py