Metadata-Version: 2.1
Name: typefactory
Version: 0.1.2
Summary: Simplify the creation and utilisation of typed and constrained value objects in Python 3
Home-page: https://github.com/stevemccartney/typefactory
Author: Steve McCartney
Author-email: python+typefactory@reconvergent.com
License: Apache-2.0
Platform: UNKNOWN
Classifier: Development Status :: 3 - Alpha
Classifier: Intended Audience :: Developers
Classifier: License :: OSI Approved :: Apache Software License
Classifier: Natural Language :: English
Classifier: Programming Language :: Python :: 3
Classifier: Programming Language :: Python :: 3.7
Classifier: Topic :: Software Development
Classifier: Topic :: Software Development :: Code Generators
Classifier: Typing :: Typed
